{"type":"object","properties":{"exercise":{"required":true,"type":"object","properties":{"title":{"type":"string","description":"The title of the exercise template.","example":"Bench Press"},"exercise_type":{"type":"enum","enum":["weight_reps","reps_only","bodyweight_reps","bodyweight_assisted_reps","duration","weight_duration","distance_duration","short_distance_weight"],"example":"weight_reps","x-readme-ref-name":"CustomExerciseType"},"equipment_category":{"description":"The equipment category of the exercise template.","example":"barbell","type":"enum","enum":["none","barbell","dumbbell","kettlebell","machine","plate","resistance_band","suspension","other"],"x-readme-ref-name":"EquipmentCategory"},"muscle_group":{"description":"The muscle group of the exercise template.","example":"chest","type":"enum","enum":["abdominals","shoulders","biceps","triceps","forearms","quadriceps","hamstrings","calves","glutes","abductors","adductors","lats","upper_back","traps","lower_back","chest","cardio","neck","full_body","other"],"x-readme-ref-name":"MuscleGroup"},"other_muscles":{"type":"array","items":{"type":"enum","enum":["abdominals","shoulders","biceps","triceps","forearms","quadriceps","hamstrings","calves","glutes","abductors","adductors","lats","upper_back","traps","lower_back","chest","cardio","neck","full_body","other"],"example":"chest","x-readme-ref-name":"MuscleGroup"},"description":"The other muscles of the exercise template.","example":["biceps","triceps"]}}}},"x-readme-ref-name":"CreateCustomExerciseRequestBody"}